cov19py/__init__.py
cov19py/client.py
cov19py-0.1.3.dist-info/WHEEL
cov19py-0.1.3.dist-info/METADATA
cov19py-0.1.3.dist-info/RECORD
