Metadata-Version: 2.1
Name: cov19py
Version: 0.1.3
Summary: 
Home-page: https://github.com/SpaceDEVofficial/corona.py
Author: SpaceDEV
Requires-Python: >=3.8,<4.0
Classifier: Programming Language :: Python :: 3
Classifier: Programming Language :: Python :: 3.8
Classifier: Programming Language :: Python :: 3.9
Requires-Dist: aiohttp (>=3.7.4,<4.0.0)
Requires-Dist: xmltodict (>=0.12.0,<0.13.0)
Project-URL: Repository, https://github.com/SpaceDEVofficial/corona.py
